assertai_alpha_deployer/__init__.py
assertai_alpha_deployer/__main__.py
assertai_alpha_deployer/script_manager.py
assertai_alpha_deployer-18.0.dist-info/METADATA
assertai_alpha_deployer-18.0.dist-info/WHEEL
assertai_alpha_deployer-18.0.dist-info/entry_points.txt
assertai_alpha_deployer-18.0.dist-info/top_level.txt
assertai_alpha_deployer-18.0.dist-info/RECORD
